{
  "id": "94a73f66-eeb9-40ee-95ca-d7c9b23fc726",
  "prevId": "00000000-0000-0000-0000-000000000000",
  "version": "5",
  "dialect": "pg",
  "tables": {
    "authors": {
      "name": "authors",
      "schema": "",
      "columns": {
        "id": {
          "name": "id",
          "type": "varchar(21)",
          "primaryKey": true,
          "notNull": true
        },
        "url": {
          "name": "url",
          "type": "varchar(255)",
          "primaryKey": false,
          "notNull": false
        },
        "name": {
          "name": "name",
          "type": "varchar(255)",
          "primaryKey": false,
          "notNull": false
        }
      },
      "indexes": {},
      "foreignKeys": {},
      "compositePrimaryKeys": {},
      "uniqueConstraints": {
        "authors_url_unique": {
          "name": "authors_url_unique",
          "nullsNotDistinct": false,
          "columns": [
            "url"
          ]
        }
      }
    },
    "choices": {
      "name": "choices",
      "schema": "",
      "columns": {
        "id": {
          "name": "id",
          "type": "varchar(21)",
          "primaryKey": true,
          "notNull": true
        },
        "question_id": {
          "name": "question_id",
          "type": "varchar(21)",
          "primaryKey": false,
          "notNull": true
        },
        "text": {
          "name": "text",
          "type": "text",
          "primaryKey": false,
          "notNull": true
        },
        "is_correct": {
          "name": "is_correct",
          "type": "boolean",
          "primaryKey": false,
          "notNull": true
        }
      },
      "indexes": {},
      "foreignKeys": {
        "choices_question_id_questions_id_fk": {
          "name": "choices_question_id_questions_id_fk",
          "tableFrom": "choices",
          "tableTo": "questions",
          "columnsFrom": [
            "question_id"
          ],
          "columnsTo": [
            "id"
          ],
          "onDelete": "no action",
          "onUpdate": "no action"
        }
      },
      "compositePrimaryKeys": {},
      "uniqueConstraints": {}
    },
    "questions": {
      "name": "questions",
      "schema": "",
      "columns": {
        "id": {
          "name": "id",
          "type": "varchar(21)",
          "primaryKey": true,
          "notNull": true
        },
        "author_id": {
          "name": "author_id",
          "type": "varchar(21)",
          "primaryKey": false,
          "notNull": false
        },
        "text": {
          "name": "text",
          "type": "text",
          "primaryKey": false,
          "notNull": true
        },
        "seconds": {
          "name": "seconds",
          "type": "integer",
          "primaryKey": false,
          "notNull": true
        },
        "explanation": {
          "name": "explanation",
          "type": "text",
          "primaryKey": false,
          "notNull": false
        }
      },
      "indexes": {},
      "foreignKeys": {
        "questions_author_id_authors_id_fk": {
          "name": "questions_author_id_authors_id_fk",
          "tableFrom": "questions",
          "tableTo": "authors",
          "columnsFrom": [
            "author_id"
          ],
          "columnsTo": [
            "id"
          ],
          "onDelete": "no action",
          "onUpdate": "no action"
        }
      },
      "compositePrimaryKeys": {},
      "uniqueConstraints": {}
    }
  },
  "enums": {},
  "schemas": {},
  "_meta": {
    "columns": {},
    "schemas": {},
    "tables": {}
  }
}